[
    {
        "id": "1",
        "question": "What is HTML?",
        "correct_answer": "All of the mentioned",
        "incorrect_answers": [
            "HTML describes the structure of a webpage=",
            "HTML is the standard markup language mainly used to create web pages",
            "All of the mentioned",
            "HTML consists of a set of elements that helps the browser how to view the content"
        ]
    },
    {
        "id": "2",
        "question": "HTML stands for____?",
        "correct_answer": "Hyper Text Markup Language",
        "incorrect_answers": [
            "HyperText Machine Language",
            "Hyper Text Markup Language",
            "HighText Marking Language",
            "HyperText Marking Language"
        ]
    },
    {
        "id": "3",
        "question": "Which element is used for or styling HTML5 layout?",
        "correct_answer": "CSS",
        "incorrect_answers": [
            "CSS",
            "jQuery",
            "JavaScript",
            "PHP"
        ]
    },
    {
        "id": "4",
        "question": "Which of the following is used to read an HTML page and render it?",
        "correct_answer": "Web browser",
        "incorrect_answers": [
            "Web browser",
            "Web server",
            "Web network",
            "Web matrix"
        ]
    },
    {
        "id": "5",
        "question": "What is DOM in HTML?",
        "correct_answer": "Convention for representing and interacting with objects in html documents",
        "incorrect_answers": [
            "Language dependent application programming",
            "Hierarchy of objects in ASP.NET",
            "Application programming interface",
            "Convention for representing and interacting with objects in html documents"
        ]
    }
]